mseep_xtquantai-0.1.1.dist-info/licenses/LICENSE
xtquantai/__init__.py
xtquantai/server.py
mseep_xtquantai-0.1.1.dist-info/METADATA
mseep_xtquantai-0.1.1.dist-info/WHEEL
mseep_xtquantai-0.1.1.dist-info/entry_points.txt
mseep_xtquantai-0.1.1.dist-info/top_level.txt
mseep_xtquantai-0.1.1.dist-info/RECORD
